{
  "content": [
    {
      "content": null,
      "created": "2022-12-08T16:38:07.516297Z",
      "format": null,
      "last_modified": "2022-12-08T16:36:38.287973Z",
      "mimetype": null,
      "name": "etf_portfolio_insights.ipynb",
      "path": "projects/Robinhood Portfolio Insights/etf_portfolio_insights.ipynb",
      "size": 46927,
      "type": "notebook",
      "writable": true
    }
  ],
  "created": "2022-12-08T16:38:07.516297Z",
  "format": "json",
  "last_modified": "2022-12-08T16:38:07.516297Z",
  "mimetype": null,
  "name": "Robinhood Portfolio Insights",
  "path": "projects/Robinhood Portfolio Insights",
  "size": null,
  "type": "directory",
  "writable": true
}