{
  "content": [
    {
      "content": null,
      "created": "2022-08-09T06:15:03.700624Z",
      "format": null,
      "last_modified": "2022-08-09T06:15:03.700624Z",
      "mimetype": null,
      "name": "projects",
      "path": "projects",
      "size": null,
      "type": "directory",
      "writable": true
    },
    {
      "content": null,
      "created": "2022-08-09T06:15:03.696624Z",
      "format": null,
      "last_modified": "2022-08-09T06:15:03.696624Z",
      "mimetype": null,
      "name": "data",
      "path": "data",
      "size": null,
      "type": "directory",
      "writable": true
    },
    {
      "content": null,
      "created": "2022-08-09T06:15:03.696624Z",
      "format": null,
      "last_modified": "2022-08-09T06:15:03.696624Z",
      "mimetype": null,
      "name": "Help",
      "path": "Help",
      "size": null,
      "type": "directory",
      "writable": true
    },
    {
      "content": null,
      "created": "2022-08-09T06:15:03.708624Z",
      "format": null,
      "last_modified": "2022-08-09T06:15:03.708624Z",
      "mimetype": null,
      "name": "pyolite",
      "path": "pyolite",
      "size": null,
      "type": "directory",
      "writable": true
    },
    {
      "content": null,
      "created": "2022-08-09T06:15:03.708624Z",
      "format": null,
      "last_modified": "2022-08-09T06:15:03.708624Z",
      "mimetype": null,
      "name": "xeus-sqlite",
      "path": "xeus-sqlite",
      "size": null,
      "type": "directory",
      "writable": true
    },
    {
      "content": null,
      "created": "2022-08-09T06:15:03.708624Z",
      "format": null,
      "last_modified": "2022-08-09T06:15:03.708624Z",
      "mimetype": null,
      "name": "xeus-wren",
      "path": "xeus-wren",
      "size": null,
      "type": "directory",
      "writable": true
    },
    {
      "content": null,
      "created": "2022-08-09T06:15:03.708624Z",
      "format": null,
      "last_modified": "2022-08-09T06:15:03.708624Z",
      "mimetype": null,
      "name": "xeus-lua",
      "path": "xeus-lua",
      "size": null,
      "type": "directory",
      "writable": true
    },
    {
      "content": null,
      "created": "2022-08-09T06:15:03.696624Z",
      "format": null,
      "last_modified": "2022-08-09T06:15:01.636584Z",
      "mimetype": "text/markdown",
      "name": "README.md",
      "path": "README.md",
      "size": 941,
      "type": "file",
      "writable": true
    }
  ],
  "created": "2022-08-09T06:15:03.708624Z",
  "format": "json",
  "last_modified": "2022-08-09T06:15:03.708624Z",
  "mimetype": null,
  "name": "",
  "path": "",
  "size": null,
  "type": "directory",
  "writable": true
}